<step title="Incoming Request" date="2025-07-28T10:56:57.217" instance="bc4514" url="/api/deployments/latest" method="GET" type="request" pid="768,1,20" Accept="*/*" Host="foodxchange-app.scm.azurewebsites.net" User-Agent="AZURECLI/2.75.0 (MSI)" Accept-Encoding="gzip, deflate" Authorization="Bas..." x-ms-client-request-id="877290c5-6ba1-11f0-824a-8cf8c504cf6c" X-ARR-LOG-ID="877290c5-6ba1-11f0-824a-8cf8c504cf6c" CLIENT-IP="95.35.178.122:57003" X-SITE-DEPLOYMENT-ID="foodxchange-app" WAS-DEFAULT-HOSTNAME="foodxchange-app.scm.azurewebsites.net" X-Forwarded-Proto="https" X-AppService-Proto="https" X-Forwarded-TlsVersion="1.3" X-WAWS-Unencoded-URL="/api/deployments/latest" X-Client-IP="95.35.178.122" X-Client-Port="57003" >
  <step title="Cleanup Xml Logs" date="2025-07-28T10:56:57.244" >
    <step title="Cleanup Infos" date="2025-07-28T10:56:57.462" totalFiles="2088" totalCleanup="1928" /><!-- duration: 68ms -->
  </step><!-- duration: 305ms -->
  <step title="DeploymentService.GetResult" date="2025-07-28T10:56:57.717" >
    <step title="DeploymentService.GetLatestDeployment" date="2025-07-28T10:56:57.748" >
      <step title="DeploymentManager.GetResults" date="2025-07-28T10:56:57.768" /><!-- duration: 3721ms -->
    </step><!-- duration: 3848ms -->
  </step><!-- duration: 3971ms -->
  <step title="Outgoing response" date="2025-07-28T10:57:01.718" type="response" statusCode="202" statusText="Accepted" /><!-- duration: 186ms -->
</step><!-- duration: 4743ms -->
