<step title="BackgroundTrace" date="2025-07-25T11:59:23.308" instance="bc4514" url="/api/publish" method="POST" >
  <step title="Cleanup Xml Logs" date="2025-07-25T11:59:23.317" >
    <step title="Cleanup Infos" date="2025-07-25T11:59:23.327" totalFiles="223" totalCleanup="63" /><!-- duration: 8ms -->
  </step><!-- duration: 20ms -->
  <step title="Creating temporary deployment - FetchDeploymentManager" date="2025-07-25T11:59:23.428" /><!-- duration: 1ms -->
  <step title="Creating temporary deployment" date="2025-07-25T11:59:23.437" /><!-- duration: 187ms -->
  <step title="Performing fetch based deployment" date="2025-07-25T11:59:23.671" >
    <step title="Cleaning up temp folders from previous zip deployments and extracting pushed zip file /tmp/zipdeploy/1bbb5792-1dd9-46a7-8309-8f3f8870e25a.zip (351.02 MB) to /tmp/zipdeploy/extracted" date="2025-07-25T11:59:25.186" >
      <step title="ChmodRecursive Process exited with total time taken in ms: 163" date="2025-07-25T11:59:36.161" /><!-- duration: 9ms -->
    </step><!-- duration: 10994ms -->
    <step title="Deployment timer started" date="2025-07-25T11:59:38.215" >
      <step title="DeploymentManager.Deploy(id:83ed9dd4-995b-42d6-bb11-7f06d5f71578)" date="2025-07-25T11:59:38.225" >
        <step title="Collecting changeset information" date="2025-07-25T11:59:38.266" /><!-- duration: 152ms -->
        <step title="Updating submodules" date="2025-07-25T11:59:38.437" /><!-- duration: 1115ms -->
        <step title="Determining deployment builder" date="2025-07-25T11:59:39.782" >
          <step title="Builder is OryxBuilder" date="2025-07-25T11:59:39.814" /><!-- duration: 8ms -->
        </step><!-- duration: 48ms -->
        <step title="PreDeployment: context.CleanOutputPath False" date="2025-07-25T11:59:39.892" >
          <step title="PreDeployment: context.OutputPath /home/site/wwwroot" date="2025-07-25T11:59:40.030" >
            <step title="Building" date="2025-07-25T11:59:40.183" >
              <step title="Executing external process" date="2025-07-25T11:59:40.449" type="process" path="bash" arguments="-c &quot;oryx build /tmp/zipdeploy/extracted -o /home/site/wwwroot --platform python --platform-version 3.12 -p virtualenv_name=antenv --log-file /tmp/build-debug.log  -i /tmp/8ddcb72bc0f807e --compress-destination-dir | tee /tmp/oryx-build.log ; exit $PIPESTATUS &quot;" >
                <step title="Cpu: python(1470,40.030s)+ts(1471,0.200s)+build.sh(1469,0.000s)+build.sh(1468,0.000s)+build.sh(1365,0.060s)+oryx(1341,4.690s)+tee(1342,0.000s)+bash(1340,0.000s)=total(44.970s)" date="2025-07-25T12:01:32.806" /><!-- duration: 38ms -->
                <step title="bash: no io activity for 61s, prev-cpu=-1.000s, current-cpu=44.970s" date="2025-07-25T12:01:32.931" /><!-- duration: 79ms -->
                <step title="Cpu: rsync(1516,2.900s)+rsync(1514,0.080s)+rsync(1513,4.230s)+build.sh(1365,0.080s)+oryx(1341,6.170s)+tee(1342,0.000s)+bash(1340,0.000s)=total(13.460s)" date="2025-07-25T12:03:05.965" /><!-- duration: 87ms -->
                <step title="bash: no io activity for 60s, prev-cpu=-1.000s, current-cpu=13.460s" date="2025-07-25T12:03:06.176" /><!-- duration: 19ms -->
                <step title="Cpu: gzip(1550,21.510s)+sh(1549,0.010s)+tar(1548,1.150s)+build.sh(1365,0.080s)+oryx(1341,6.710s)+tee(1342,0.000s)+bash(1340,0.000s)=total(29.440s)" date="2025-07-25T12:04:19.333" /><!-- duration: 38ms -->
                <step title="bash: no io activity for 60s, prev-cpu=-1.000s, current-cpu=29.440s" date="2025-07-25T12:04:19.518" /><!-- duration: 2ms -->
                <step title="Cpu: gzip(1550,52.100s)+sh(1549,0.010s)+tar(1548,2.870s)+build.sh(1365,0.080s)+oryx(1341,7.360s)+tee(1342,0.000s)+bash(1340,0.000s)=total(62.410s)" date="2025-07-25T12:05:19.936" /><!-- duration: 18ms -->
                <step title="bash: no io activity for 121s, prev-cpu=29.440s, current-cpu=62.410s" date="2025-07-25T12:05:19.982" /><!-- duration: 3ms -->
                <step title="Cpu: gzip(1550,81.260s)+sh(1549,0.010s)+tar(1548,4.320s)+build.sh(1365,0.080s)+oryx(1341,7.620s)+tee(1342,0.000s)+bash(1340,0.000s)=total(93.290s)" date="2025-07-25T12:06:20.647" /><!-- duration: 11ms -->
                <step title="bash: no io activity for 182s, prev-cpu=62.410s, current-cpu=93.290s" date="2025-07-25T12:06:20.667" /><!-- duration: 9ms -->
              </step><!-- duration: 403543ms -->
              <step title="Using PythonDeploymentLogParser" date="2025-07-25T12:06:24.353" /><!-- duration: 7ms -->
              <step title="Modified file to trigger a restart of the app container." date="2025-07-25T12:06:25.518" /><!-- duration: 2ms -->
              <step title="Skip function trigger and logicapp sync because function is not enabled." date="2025-07-25T12:06:25.532" /><!-- duration: 11ms -->
            </step><!-- duration: 406229ms -->
          </step><!-- duration: 406384ms -->
          <step title="Cleaning up temp files" date="2025-07-25T12:06:26.416" /><!-- duration: 1105ms -->
          <step title="Cleaning up temp files" date="2025-07-25T12:06:27.523" /><!-- duration: 507ms -->
          <step title="Reloading status file with latest updates" date="2025-07-25T12:06:28.067" >
            <step title="WebHooksManager.PublishEventAsync: PostDeployment" date="2025-07-25T12:06:28.076" /><!-- duration: 46ms -->
          </step><!-- duration: 56ms -->
          <step title="Cleaning up temporary deployment - fetch deployment was successful" date="2025-07-25T12:06:28.144" /><!-- duration: 10ms -->
        </step><!-- duration: 408341ms -->
      </step><!-- duration: 410027ms -->
