<step title="BackgroundTrace" date="2025-07-28T10:56:47.034" instance="bc4514" url="/api/zipdeploy" method="POST" >
  <step title="Cleanup Xml Logs" date="2025-07-28T10:56:47.037" >
    <step title="Cleanup Infos" date="2025-07-28T10:56:47.167" totalFiles="2086" totalCleanup="1926" /><!-- duration: 11ms -->
  </step><!-- duration: 149ms -->
  <step title="Creating temporary deployment - FetchDeploymentManager" date="2025-07-28T10:56:47.322" /><!-- duration: 1ms -->
  <step title="Creating temporary deployment" date="2025-07-28T10:56:47.350" /><!-- duration: 87ms -->
  <step title="Performing fetch based deployment" date="2025-07-28T10:56:47.576" >
    <step title="Cleaning up temp folders from previous zip deployments and extracting pushed zip file /tmp/zipdeploy/d3efdc92-b649-4268-af0a-974f58526ffc.zip (5.05 MB) to /tmp/zipdeploy/extracted" date="2025-07-28T10:56:48.856" >
      <step title="ChmodRecursive Process exited with total time taken in ms: 151" date="2025-07-28T10:56:50.810" /><!-- duration: 10ms -->
    </step><!-- duration: 1972ms -->
    <step title="Deployment timer started" date="2025-07-28T10:56:52.875" >
      <step title="DeploymentManager.Deploy(id:d7bfd21b-2809-435e-95c3-70bc556238b6)" date="2025-07-28T10:56:53.022" >
        <step title="Collecting changeset information" date="2025-07-28T10:56:53.178" /><!-- duration: 1695ms -->
        <step title="Updating submodules" date="2025-07-28T10:56:54.952" /><!-- duration: 1406ms -->
        <step title="Determining deployment builder" date="2025-07-28T10:56:56.988" >
          <step title="Builder is BasicBuilder" date="2025-07-28T10:56:57.064" /><!-- duration: 2ms -->
        </step><!-- duration: 89ms -->
        <step title="PreDeployment: context.CleanOutputPath False" date="2025-07-28T10:56:57.244" >
          <step title="PreDeployment: context.OutputPath /home/site/wwwroot" date="2025-07-28T10:56:57.527" >
            <step title="Building" date="2025-07-28T10:56:57.897" >
              <step title="Executing external process" date="2025-07-28T10:56:58.923" type="process" path="starter.sh" arguments="/opt/Kudu/Scripts/parallel_rsync.sh /tmp/zipdeploy/extracted /home/site/wwwroot 8 /tmp/ False True  " /><!-- duration: 27198ms -->
              <step title="Triggering recycle (preview mode disabled)." date="2025-07-28T10:57:26.630" /><!-- duration: 11ms -->
              <step title="Modified file to trigger a restart of the app container." date="2025-07-28T10:57:26.738" /><!-- duration: 2ms -->
              <step title="Skip function trigger and logicapp sync because function is not enabled." date="2025-07-28T10:57:26.759" /><!-- duration: 1ms -->
              <step title="Purge deployment items" date="2025-07-28T10:57:31.712" >
                <step title="Remove 9c56ea3b-, Success, received at 07/27/2025 14:39:39" date="2025-07-28T10:57:31.905" /><!-- duration: 1ms -->
              </step><!-- duration: 254ms -->
            </step><!-- duration: 34185ms -->
          </step><!-- duration: 34593ms -->
          <step title="Cleaning up temp files" date="2025-07-28T10:57:32.122" /><!-- duration: 26ms -->
          <step title="Cleaning up temp files" date="2025-07-28T10:57:32.165" /><!-- duration: 586ms -->
          <step title="Reloading status file with latest updates" date="2025-07-28T10:57:32.817" >
            <step title="WebHooksManager.PublishEventAsync: PostDeployment" date="2025-07-28T10:57:32.837" /><!-- duration: 49ms -->
          </step><!-- duration: 78ms -->
          <step title="Cleaning up temporary deployment - fetch deployment was successful" date="2025-07-28T10:57:32.972" /><!-- duration: 3ms -->
        </step><!-- duration: 35894ms -->
      </step><!-- duration: 40215ms -->
